{
  "data": [
    {
      "id": 1662199724562,
      "username": "",
      "password": ""
    },
    {
      "id": 1662199762254,
      "username": "qwe",
      "password": "qwe"
    },
    {
      "id": 1662202293289,
      "username": "",
      "password": ""
    }
  ],
  "post": [
    {
      "title": "qwe",
      "body": "qwe",
      "id": 1
    },
    {
      "title": "qwe",
      "body": "qwe",
      "id": 2
    },
    {
      "title": "qwe",
      "body": "qwe",
      "id": 3
    },
    {
      "title": "ㅂㅈㄷ",
      "body": "ㅂㅈㄷ",
      "imagefile": "",
      "id": 4
    }
  ]
}